<PAMDataset>
  <Metadata>
    <MDI key="DataType">Generic</MDI>
  </Metadata>
  <PAMRasterBand band="1">
    <Histograms>
      <HistItem>
        <HistMin>-3</HistMin>
        <HistMax>2940.25</HistMax>
        <BucketCount>256</BucketCount>
        <IncludeOutOfRange>1</IncludeOutOfRange>
        <Approximate>0</Approximate>
        <HistCounts>6|12|36|75|86|82|80|63|64|70|63|56|58|53|61|111|202|638|1493|2657|4059|5735|7295|8980|9855|10679|10567|10601|10252|9444|8620|7852|7239|6353|5976|5510|5084|4798|4339|3990|3653|3599|3011|2756|2542|2407|2182|2013|2007|1812|1731|1571|1509|1420|1301|1250|1165|1107|1116|1147|1002|977|925|891|841|836|745|705|703|619|652|626|575|602|539|573|538|502|476|445|426|405|448|428|368|357|351|355|352|344|320|307|288|261|299|305|272|294|281|227|257|252|236|226|220|219|213|204|191|165|205|195|190|176|189|171|162|164|153|143|164|140|154|136|144|142|118|134|135|125|136|125|132|115|109|102|127|104|105|113|79|106|106|91|91|81|83|113|87|95|102|65|84|77|74|76|75|61|47|78|61|47|68|40|53|46|64|52|45|50|39|42|57|36|44|36|41|39|42|39|34|40|44|34|35|44|46|32|37|39|27|33|33|25|25|29|24|19|26|16|24|20|20|18|19|18|11|21|22|24|16|16|12|14|18|16|14|19|10|11|10|6|5|10|5|5|4|4|5|3|1|2|3|2|0|1|0|0|1|0|0|1|0|0|0|0|0|0|1|0|0|1|0|0|0|1</HistCounts>
      </HistItem>
    </Histograms>
    <Metadata>
      <MDI key="RepresentationType">THEMATIC</MDI>
      <MDI key="STATISTICS_COVARIANCES">94019.76756764561</MDI>
      <MDI key="STATISTICS_EXCLUDEDVALUES"></MDI>
      <MDI key="STATISTICS_MAXIMUM">2940.25</MDI>
      <MDI key="STATISTICS_MEAN">472.3398226003</MDI>
      <MDI key="STATISTICS_MEDIAN">366.349020</MDI>
      <MDI key="STATISTICS_MINIMUM">-3</MDI>
      <MDI key="STATISTICS_SKIPFACTORX">1</MDI>
      <MDI key="STATISTICS_SKIPFACTORY">1</MDI>
      <MDI key="STATISTICS_STDDEV">306.62642998875</MDI>
    </Metadata>
  </PAMRasterBand>
</PAMDataset>
