<PAMDataset>
  <Metadata>
    <MDI key="DataType">Generic</MDI>
  </Metadata>
  <PAMRasterBand band="1">
    <Histograms>
      <HistItem>
        <HistMin>108.7777786254883</HistMin>
        <HistMax>6720</HistMax>
        <BucketCount>256</BucketCount>
        <IncludeOutOfRange>1</IncludeOutOfRange>
        <Approximate>0</Approximate>
        <HistCounts>34|61|59|57|47|42|37|42|50|26|34|34|51|54|52|33|45|52|48|41|33|38|34|30|44|23|32|23|25|23|43|26|26|41|21|35|43|30|29|27|26|28|36|31|33|25|33|37|31|33|30|38|48|61|69|63|88|93|106|134|204|230|308|366|422|545|652|757|925|1031|1237|1386|1518|1702|1809|2003|1996|2203|2368|2633|2734|2749|2920|3058|3129|3339|3460|3572|3795|3791|3853|3909|3885|4143|4173|4199|4029|4123|4076|3907|3943|3925|3826|3774|3777|3559|3369|3345|3186|3030|3093|2953|2868|2909|2746|2555|2551|2468|2463|2373|2278|2337|2270|2179|2133|2135|2024|1991|1960|1879|1810|1788|1648|1680|1605|1510|1535|1496|1456|1418|1337|1264|1228|1262|1182|1124|974|998|991|908|842|759|775|692|658|613|534|553|496|483|449|431|355|385|346|298|289|252|257|200|204|198|180|167|153|150|119|111|101|94|81|88|88|79|71|66|34|56|49|55|39|48|35|29|32|30|31|15|18|16|24|20|15|6|8|11|17|6|7|9|11|7|3|6|5|6|5|1|1|2|1|2|1|1|0|1|1|1|1|1|0|0|2|0|0|2|0|0|1|0|0|0|0|1|0|1|0|0|0|0|0|0|0|0|0|1</HistCounts>
      </HistItem>
    </Histograms>
    <Metadata>
      <MDI key="RepresentationType">THEMATIC</MDI>
      <MDI key="STATISTICS_COVARIANCES">429158.5203976628</MDI>
      <MDI key="STATISTICS_EXCLUDEDVALUES"></MDI>
      <MDI key="STATISTICS_MAXIMUM">6720</MDI>
      <MDI key="STATISTICS_MEAN">2867.6064201384</MDI>
      <MDI key="STATISTICS_MEDIAN">2779.193029</MDI>
      <MDI key="STATISTICS_MINIMUM">108.77777862549</MDI>
      <MDI key="STATISTICS_SKIPFACTORX">1</MDI>
      <MDI key="STATISTICS_SKIPFACTORY">1</MDI>
      <MDI key="STATISTICS_STDDEV">655.10191603877</MDI>
    </Metadata>
  </PAMRasterBand>
</PAMDataset>
